brainannex/__init__.py
brainannex/categories.py
brainannex/collections.py
brainannex/cypher_utils.py
brainannex/exceptions.py
brainannex/full_text_indexing.py
brainannex/neoaccess.py
brainannex/neoschema.py
brainannex/py_graph_visual.py
brainannex/user_manager.py
brainannex/intergraph_neo4j_4/intergraph_neo4j_4.py
brainannex_neo4jv4-5.0rc5.dist-info/METADATA
brainannex_neo4jv4-5.0rc5.dist-info/WHEEL
brainannex_neo4jv4-5.0rc5.dist-info/licenses/LICENSE.txt
brainannex_neo4jv4-5.0rc5.dist-info/RECORD
