Metadata-Version: 2.4
Name: brainannex-neo4jv4
Version: 5.0rc5
Summary: Full-Stack Data/Knowledge Management with Neo4j
Project-URL: Homepage, https://brainannex.org
Project-URL: Home-page, https://brainannex.org
Project-URL: Bug Tracker, https://github.com/BrainAnnex/brain-annex/issues
Project-URL: Source, https://github.com/BrainAnnex/brain-annex
Project-URL: Documentation, https://brainannex.org
Author: Julian West BrainAnnex.org
Maintainer-email: julian@brainannex.org
License-Expression: MIT
License-File: LICENSE.txt
Keywords: graph database,knowledge graph,neo4j
Classifier: License :: OSI Approved :: MIT License
Classifier: Operating System :: OS Independent
Classifier: Programming Language :: Python :: 3
Requires-Python: >=3.9
Requires-Dist: bcrypt==4.1.2
Requires-Dist: neo4j~=4.4.12
Requires-Dist: numpy~=1.26.4
Requires-Dist: pandas~=1.5.3
Requires-Dist: pillow~=10.3.0
Requires-Dist: pymupdf~=1.23.5
Requires-Dist: requests~=2.28.2
